emptyorchestra/__init__.py
emptyorchestra/eo_conf.yml
emptyorchestra/eo_web.py
emptyorchestra/id3reader.py
emptyorchestra/youtube.py
emptyorchestra/static/applause.mp3
emptyorchestra/static/css/general.css
emptyorchestra/static/css/karaoke.css
emptyorchestra/static/css/layout.css
emptyorchestra/static/css/main.css
emptyorchestra/static/css/simplegrid.css
emptyorchestra/static/css/widgets.css
emptyorchestra/static/images/bg_ampitheater1.jpeg
emptyorchestra/static/images/bg_bar1.jpeg
emptyorchestra/static/images/bg_concert1.jpeg
emptyorchestra/static/images/bg_concert2.jpeg
emptyorchestra/static/images/bg_theater1.jpeg
emptyorchestra/static/images/kj_1.jpeg
emptyorchestra/static/images/next_2.jpeg
emptyorchestra/static/images/next_mic1.jpeg
emptyorchestra/static/images/next_mic2.jpeg
emptyorchestra/static/images/paper1.jpeg
emptyorchestra/static/js/ajax_stuff.js
emptyorchestra/static/js/jquery-1.3.2.min.js
emptyorchestra/static/js/jquery.corner.js
emptyorchestra/static/js/jquery.form.js
emptyorchestra/static/js/jquery.js
emptyorchestra/static/js/json2.js
emptyorchestra/static/js/superfish.js
emptyorchestra/static/js/wcdg.js
emptyorchestra/static/tracks/funkeriffic.mp3
emptyorchestra/static/tracks/martinisunset.mp3
emptyorchestra/static/tracks/sundaydub.mp3
emptyorchestra/static/tracks/uberpunch.mp3
emptyorchestra/templates/all_singers.html
emptyorchestra/templates/control.html
emptyorchestra/templates/eo.js
emptyorchestra/templates/index.html
emptyorchestra/templates/karaoke.html
emptyorchestra/templates/layout.html
emptyorchestra/templates/local_results.html
emptyorchestra/templates/local_songs.html
emptyorchestra/templates/player.html
emptyorchestra/templates/queue.html
emptyorchestra/templates/sing.html
emptyorchestra/templates/singerdata.html
emptyorchestra/templates/song_dialog.html
emptyorchestra/templates/web_results.html
emptyorchestra-0.1.0.dist-info/METADATA
emptyorchestra-0.1.0.dist-info/WHEEL
emptyorchestra-0.1.0.dist-info/entry_points.txt
emptyorchestra-0.1.0.dist-info/top_level.txt
emptyorchestra-0.1.0.dist-info/RECORD
