Metadata-Version: 2.1
Name: emptyorchestra
Version: 0.1.0
Summary: UNKNOWN
Home-page: http://emptyorchestra.kubilus.net
Author: Matt Kubilus
Author-email: mattkubilus@gmail.com
License: UNKNOWN
Platform: UNKNOWN
Requires-Dist: Flask (>=0.12)
Requires-Dist: gTTS (==2.0.1)
Requires-Dist: jinja2 (<3.0)
Requires-Dist: pywebview (>=3.0)
Requires-Dist: pyyaml
Requires-Dist: tinydb (>=3.7)
Requires-Dist: xmltodict (<0.12)
